{"digest":"b4ea2f383a74e03627537c7388320d90b9fb02f7","css":"atom-text-editor,\n:host {\n  background-color: #263238;\n  color: #d4d6d7;\n}\natom-text-editor .wrap-guide,\n:host .wrap-guide {\n  background-color: #333f46;\n}\natom-text-editor .indent-guide,\n:host .indent-guide {\n  color: #333f46;\n}\natom-text-editor .invisible-character,\n:host .invisible-character {\n  color: #333f46;\n}\natom-text-editor .gutter,\n:host .gutter {\n  background-color: #263238;\n  color: #526069;\n}\natom-text-editor .gutter .line-number.cursor-line,\n:host .gutter .line-number.cursor-line {\n  background-color: #333f46;\n  color: #526069;\n}\natom-text-editor .gutter .line-number.cursor-line-no-selection,\n:host .gutter .line-number.cursor-line-no-selection {\n  color: #526069;\n}\natom-text-editor .gutter .line-number.folded,\n:host .gutter .line-number.folded,\natom-text-editor .gutter .line-number:after,\n:host .gutter .line-number:after,\natom-text-editor .fold-marker:after,\n:host .fold-marker:after {\n  color: #526069;\n}\natom-text-editor .invisible,\n:host .invisible {\n  color: #d4d6d7;\n}\natom-text-editor .cursor,\n:host .cursor {\n  color: #ffffff;\n}\natom-text-editor .selection .region,\n:host .selection .region {\n  background-color: #3b4d56;\n}\natom-text-editor .search-results .marker .region,\n:host .search-results .marker .region {\n  background-color: transparent;\n  border: 1px solid #526069;\n}\natom-text-editor .search-results .marker.current-result .region,\n:host .search-results .marker.current-result .region {\n  border: 1px solid #ffffff;\n}\n.comment {\n  color: #526069;\n}\n.entity.name.type {\n  color: #ffeb95;\n}\n.entity.other.inherited-class {\n  color: #c3e88d;\n}\n.keyword {\n  color: #bb80b3;\n}\n.keyword.control {\n  color: #ec5f67;\n}\n.keyword.control.php {\n  color: #bb80b3;\n}\n.keyword.control.at-rule {\n  color: #bb80b3;\n}\n.keyword.control.at-rule .keyword {\n  color: #80cbc4;\n}\n.keyword.operator {\n  color: #80cbc4;\n}\n.keyword.other.special-method {\n  color: #6699cc;\n}\n.keyword.other.unit {\n  color: #ffeb95;\n}\n.storage {\n  color: #bb80b3;\n}\n.storage.modifier.php {\n  color: #d4d6d7;\n}\n.constant {\n  color: #ffeb95;\n}\n.constant.character.escape {\n  color: #80cbc4;\n}\n.constant.numeric {\n  color: #ffeb95;\n}\n.constant.other.color {\n  color: #80cbc4;\n}\n.constant.other.symbol {\n  color: #c3e88d;\n}\n.type {\n  color: #bb80b3;\n}\n.type.property-name {\n  color: #80cbc4;\n}\n.variable {\n  color: #ec5f67;\n}\n.variable.other {\n  color: #d4d6d7;\n}\n.variable.other.less {\n  color: #ec5f67;\n}\n.variable.parameter.function {\n  color: #ffeb95;\n}\n.invalid.illegal {\n  background-color: #ec5f67;\n  color: #263238;\n}\n.string {\n  color: #c3e88d;\n}\n.string.regexp {\n  color: #80cbc4;\n}\n.string.regexp .source.ruby.embedded {\n  color: #e8a01e;\n}\n.string.other.link {\n  color: #ec5f67;\n}\n.punctuation.definition.comment {\n  color: #526069;\n}\n.punctuation.definition.begin,\n.punctuation.definition.end {\n  color: #80cbc4;\n}\n.punctuation.definition.string,\n.punctuation.definition.variable,\n.punctuation.definition.parameters,\n.punctuation.definition.array {\n  color: #80cbc4;\n}\n.punctuation.definition.heading,\n.punctuation.definition.identity {\n  color: #6699cc;\n}\n.punctuation.definition.bold {\n  color: #ffeb95;\n  font-weight: bold;\n}\n.punctuation.definition.italic {\n  color: #bb80b3;\n  font-style: italic;\n}\n.punctuation.section.embedded {\n  color: #ffeb95;\n}\n.support.class {\n  color: #bb80b3;\n}\n.support.function {\n  color: #6699cc;\n}\n.entity.name.function {\n  color: #6699cc;\n}\n.entity.name.class,\n.entity.name.type.class {\n  color: #ffeb95;\n}\n.entity.name.section {\n  color: #6699cc;\n}\n.entity.name.tag {\n  color: #ec5f67;\n}\n.entity.other.attribute-name {\n  color: #80cbc4;\n}\n.entity.other.attribute-name.class {\n  color: #c3e88d;\n}\n.entity.other.attribute-name.id {\n  color: #e8a01e;\n}\n.meta.class {\n  color: #ffeb95;\n}\n.meta.link {\n  color: #e8a01e;\n}\n.meta.function-call,\n.meta.require {\n  color: #6699cc;\n}\n.meta.selector {\n  color: #bb80b3;\n}\n.meta.tag {\n  color: #80cbc4;\n}\n.meta.separator {\n  background-color: #333f46;\n  color: #d4d6d7;\n}\n.none {\n  color: #d4d6d7;\n}\n.markup.bold {\n  color: #e8a01e;\n  font-weight: bold;\n}\n.markup.changed {\n  color: #bb80b3;\n}\n.markup.deleted {\n  color: #ec5f67;\n}\n.markup.italic {\n  color: #bb80b3;\n  font-style: italic;\n}\n.markup.heading .punctuation.definition.heading {\n  color: #6699cc;\n}\n.markup.inserted {\n  color: #c3e88d;\n}\n.markup.list {\n  color: #ec5f67;\n}\n.markup.quote {\n  color: #e8a01e;\n}\n.markup.raw.inline {\n  color: #c3e88d;\n}\n.source.gfm .markup {\n  -webkit-font-smoothing: auto;\n}\n.source.gfm .markup.heading {\n  color: #c3e88d;\n}\n.source.gfm .markup.heading .marker {\n  color: #80cbc4;\n}\natom-text-editor[mini] .scroll-view,\n:host([mini]) .scroll-view {\n  padding-left: 1px;\n}\n","imports":[{"path":"static\\variables\\ui-variables.less","digest":"a51b652b59d33fcd2efa2fd725a78735dbbcf655"},{"path":"static\\variables\\syntax-variables.less","digest":"161404ff92113205d84a38441681ded1e4527102"},{"path":"C:\\Users\\Maxemilian\\.atom\\packages\\material-syntax\\styles\\base.less","digest":"ff55fda64078a44cf6f89d46d44ac73d66e4e98b"},{"path":"C:\\Users\\Maxemilian\\.atom\\packages\\material-syntax\\styles\\syntax-variables.less","digest":"95f510e23088ac111280f5747650a36233a3048b"},{"path":"C:\\Users\\Maxemilian\\.atom\\packages\\material-syntax\\styles\\colors.less","digest":"f89cb140aeecc6a43e999f2f264a73de5323b01d"}],"version":1}